{
  "lessonInfo": {
    "textbook": "donga-yoon-22-g1",
    "lesson": 3,
    "title": "Lesson 3"
  },
  "words": [
    {"en": "wrong", "ko": "잘못된", "pos": "a.", "ex": "Something is wrong with my phone."},
    {"en": "worried", "ko": "걱정하는", "pos": "a.", "ex": "He looks worried about something."},
    {"en": "sorry", "ko": "유감인, 미안한", "pos": "a.", "ex": "I'm sorry to hear that."},
    {"en": "should", "ko": "~해야 한다", "pos": "aux.", "ex": "You should make a spending plan."},
    {"en": "excited", "ko": "신이 난", "pos": "a.", "ex": "We're excited about the new game."},
    {"en": "work", "ko": "작동하다, 일하다", "pos": "v.", "ex": "My robot is not working now."},
    {"en": "present", "ko": "선물", "pos": "n.", "ex": "Hyein is happy with your present."},
    {"en": "upset", "ko": "속상한", "pos": "a.", "ex": "I'm upset about my test results."},
    {"en": "win", "ko": "이기다, (상을) 타다", "pos": "v.", "ex": "Our team won the first game."},
    {"en": "congratulation", "ko": "축하", "pos": "n.", "ex": "Congratulations on your award!"},
    {"en": "well", "ko": "건강한", "pos": "a.", "ex": "I'm not feeling well today."},
    {"en": "work on", "ko": "애쓰다, 노력하다", "pos": "", "ex": "No one is working on the problem."},
    {"en": "project", "ko": "연구 과제", "pos": "n.", "ex": "We have a group project this week."},
    {"en": "fair", "ko": "박람회, 공평한", "pos": "n./a.", "ex": "The local fair had many fun activities."},
    {"en": "prize", "ko": "상", "pos": "n.", "ex": "She won a prize in the drawing contest."},
    {"en": "hard", "ko": "열심히, 어려운", "pos": "adv./a.", "ex": "He studied hard for the final exam."},
    {"en": "cheer up", "ko": "기운을 내다", "pos": "", "ex": "Cheer up! Everything will be okay."},
    {"en": "do one's best", "ko": "최선을 다하다", "pos": "", "ex": "He did his best during difficult times."},
    {"en": "learn", "ko": "배우다", "pos": "v.", "ex": "We learn from our mistakes."},
    {"en": "a lot", "ko": "많이", "pos": "adv.", "ex": "Gyesoo and I talk a lot during lunch."},
    {"en": "green", "ko": "환경 친화적인", "pos": "a.", "ex": "They live a green lifestyle."},
    {"en": "energy", "ko": "에너지", "pos": "n.", "ex": "Solar energy is clean and free."},
    {"en": "positive", "ko": "긍정적인", "pos": "a.", "ex": "She is always positive."},
    {"en": "attitude", "ko": "태도", "pos": "n.", "ex": "His attitude towards life changed."},
    {"en": "result", "ko": "결과", "pos": "n.", "ex": "The result of the game is 2-0."},
    {"en": "hold", "ko": "열다, 개최하다", "pos": "v.", "ex": "Our school holds a concert every year."},
    {"en": "contest", "ko": "대회", "pos": "n.", "ex": "Will you enter the singing contest?"},
    {"en": "enter", "ko": "참가하다, 들어가다", "pos": "v.", "ex": "They entered the race."},
    {"en": "kid", "ko": "농담하다, 아이", "pos": "v./n.", "ex": "He is kidding about the surprise party."},
    {"en": "terrible", "ko": "형편없는, 끔찍한", "pos": "a.", "ex": "The service was terrible."},
    {"en": "dancer", "ko": "춤을 추는 사람", "pos": "n.", "ex": "She is a wonderful dancer."},
    {"en": "interested", "ko": "관심이 있는", "pos": "a.", "ex": "I am interested in science and math."},
    {"en": "guess", "ko": "추측하다", "pos": "v.", "ex": "Can you guess the answer?"},
    {"en": "happen", "ko": "(일이) 발생하다", "pos": "v.", "ex": "A strange thing happened this morning."},
    {"en": "next", "ko": "다음에", "pos": "adv.", "ex": "What happens next?"},
    {"en": "following", "ko": "다음에 나오는", "pos": "a.", "ex": "Answer the following question."},
    {"en": "different", "ko": "다른", "pos": "a.", "ex": "She has a different opinion."},
    {"en": "situation", "ko": "상황", "pos": "n.", "ex": "The situation is getting better."},
    {"en": "teammate", "ko": "팀원", "pos": "n.", "ex": "She has good teammates."},
    {"en": "practice", "ko": "연습하다, 연습", "pos": "v./n.", "ex": "She practices piano for two hours every day."},
    {"en": "mistake", "ko": "실수", "pos": "n.", "ex": "We learn from mistakes."},
    {"en": "make a mistake", "ko": "실수를 하다", "pos": "", "ex": "Everyone makes mistakes sometimes."},
    {"en": "hopeless", "ko": "가망 없는, 절망적인", "pos": "a.", "ex": "She felt hopeless after the exam."},
    {"en": "by the way", "ko": "그런데", "pos": "", "ex": "I saw John at the store, by the way."},
    {"en": "sick", "ko": "아픈", "pos": "a.", "ex": "I feel sick today."},
    {"en": "text", "ko": "문자를 보내다", "pos": "v.", "ex": "I texted my mom about dinner plans."},
    {"en": "see", "ko": "보다", "pos": "v.", "ex": "Can you see the rainbow?"},
    {"en": "all right", "ko": "괜찮은", "pos": "a.", "ex": "I feel all right now."},
    {"en": "tired", "ko": "피곤한", "pos": "a.", "ex": "I'm very tired today."},
    {"en": "get anywhere", "ko": "진전을 이루다", "pos": "", "ex": "You won't get anywhere without hard work."},
    {"en": "waste", "ko": "낭비하다, 쓰레기", "pos": "v./n.", "ex": "Don't waste water."},
    {"en": "fault", "ko": "잘못", "pos": "n.", "ex": "The accident was his fault."},
    {"en": "quit", "ko": "그만두다", "pos": "v.", "ex": "He quit his bad habits."},
    {"en": "unhappy", "ko": "불만스러운", "pos": "a.", "ex": "They were unhappy with their room."},
    {"en": "finally", "ko": "마침내", "pos": "adv.", "ex": "She finally passed the exam."},
    {"en": "worry", "ko": "걱정하다", "pos": "v.", "ex": "Parents often worry about their children."},
    {"en": "almost", "ko": "거의", "pos": "adv.", "ex": "The project is almost done."},
    {"en": "over", "ko": "끝이 난", "pos": "a.", "ex": "The concert is over."},
    {"en": "make it", "ko": "성공하다, 해내다", "pos": "", "ex": "She worked hard and finally made it."},
    {"en": "finish", "ko": "끝내다, 마치다", "pos": "v.", "ex": "I finished my homework before bed."},
    {"en": "without", "ko": "~없이", "pos": "prep.", "ex": "I can't live without music."},
    {"en": "proud", "ko": "자랑스러운", "pos": "a.", "ex": "I'm proud of you."},
    {"en": "be proud of", "ko": "~을 자랑스러워하다", "pos": "", "ex": "She is proud of her parents."},
    {"en": "support", "ko": "응원, 지지", "pos": "n.", "ex": "I need your support."}
  ]
}
